jpyfig-0.3.0.dist-info/licenses/LICENSE
pyfig/__init__.py
pyfig/_debug.py
pyfig/_debug_test.py
pyfig/_evaluate_conf.py
pyfig/_evaluate_conf_test.py
pyfig/_loader.py
pyfig/_loader_test.py
pyfig/_metaconf.py
pyfig/_metaconf_test.py
pyfig/_override.py
pyfig/_override_test.py
pyfig/_pyfig.py
pyfig/_pyfig_test.py
pyfig/_eval/__init__.py
pyfig/_eval/abstract_evaluator.py
pyfig/_eval/cat_evaluator.py
pyfig/_eval/cat_evaluator_test.py
pyfig/_eval/environment_evaluator.py
pyfig/_eval/environment_evaluator_test.py
pyfig/_eval/jsonfile_evaluator.py
pyfig/_eval/jsonfile_evaluator_test.py
pyfig/_eval/python_evaluator.py
pyfig/_eval/python_evaluator_test.py
pyfig/_eval/string_evaluator.py
pyfig/_eval/string_evaluator_test.py
pyfig/_eval/sympy_evaluator.py
pyfig/_eval/sympy_evaluator_test.py
pyfig/_eval/variable_evaluator.py
pyfig/_eval/variable_evaluator_test.py
pyfig/_eval/yamlfile_evaluator.py
pyfig/_eval/yamlfile_evaluator_test.py
jpyfig-0.3.0.dist-info/METADATA
jpyfig-0.3.0.dist-info/WHEEL
jpyfig-0.3.0.dist-info/top_level.txt
jpyfig-0.3.0.dist-info/RECORD
