Metadata-Version: 2.4
Name: jpyfig
Version: 0.3.0
Summary: Configuration library built around pydantic
Home-page: https://github.com/just1ngray/pyfig
Author: Justin Gray
Author-email: just1ngray@outlook.com
License: MIT
License-File: LICENSE
Requires-Dist: pydantic<3.0.0,>=2.0.0
Dynamic: author
Dynamic: author-email
Dynamic: description
Dynamic: description-content-type
Dynamic: home-page
Dynamic: license
Dynamic: license-file
Dynamic: requires-dist
Dynamic: summary
